lib_handler/__init__.py
lib_handler/main.py
lib_handler_romakot-0.0.3.dist-info/LICENSE
lib_handler_romakot-0.0.3.dist-info/METADATA
lib_handler_romakot-0.0.3.dist-info/WHEEL
lib_handler_romakot-0.0.3.dist-info/top_level.txt
lib_handler_romakot-0.0.3.dist-info/RECORD
