Metadata-Version: 2.1
Name: lib-handler-romakot
Version: 0.0.3
Summary: Handler for me
Home-page: https://github.com/romakot321/gamedev
Author: romakot
Author-email: dota234con@mail.ru
License: UNKNOWN
Platform: UNKNOWN
Classifier: Programming Language :: Python :: 3
Classifier: License :: OSI Approved :: MIT License
Classifier: Operating System :: OS Independent
Requires-Python: >=3.6
